[
    {
        "id": 1,
        "date": "2024-01-21 16:47:06.012427",
        "title": "Начало",
        "text": "Контрольное Задание на Python"
    },
    {
        "id": 2,
        "date": "2024-01-21 16:48:01.852989",
        "title": "Задание",
        "text": "Написать проект, содержащий функционал работы с заметками"
    },
    {
        "id": 3,
        "date": "2024-01-21 16:55:13.933934",
        "title": "Функционал 1-2",
        "text": "Создавать заметку и сохранять её"
    },
    {
        "id": 4,
        "date": "2024-01-21 16:56:14.453385",
        "title": "Функционал 3-4",
        "text": "редактировать заметку, удалять её"
    },
    {
        "id": 5,
        "date": "2024-01-21 16:56:58.316581",
        "title": "Функционал 5",
        "text": "предоставлять список всех заметок"
    },
    {
        "id": 6,
        "date": "2024-01-21 19:22:00.247746",
        "title": "testing",
        "text": "tester"
    }
]